qiskit_code_assistant_jupyterlab/__init__.py
qiskit_code_assistant_jupyterlab/_version.py
qiskit_code_assistant_jupyterlab/handlers.py
qiskit_code_assistant_jupyterlab-0.9.0.data/data/etc/jupyter/jupyter_server_config.d/qiskit_code_assistant_jupyterlab.json
qiskit_code_assistant_jupyterlab-0.9.0.data/data/share/jupyter/labextensions/qiskit-code-assistant-jupyterlab/package.json
qiskit_code_assistant_jupyterlab-0.9.0.data/data/share/jupyter/labextensions/qiskit-code-assistant-jupyterlab/schemas/qiskit-code-assistant-jupyterlab/package.json.orig
qiskit_code_assistant_jupyterlab-0.9.0.data/data/share/jupyter/labextensions/qiskit-code-assistant-jupyterlab/schemas/qiskit-code-assistant-jupyterlab/plugin.json
qiskit_code_assistant_jupyterlab-0.9.0.data/data/share/jupyter/labextensions/qiskit-code-assistant-jupyterlab/static/511.72fec71c71647114a18d.js
qiskit_code_assistant_jupyterlab-0.9.0.data/data/share/jupyter/labextensions/qiskit-code-assistant-jupyterlab/static/728.93aca39ae0bd9b07f548.js
qiskit_code_assistant_jupyterlab-0.9.0.data/data/share/jupyter/labextensions/qiskit-code-assistant-jupyterlab/static/remoteEntry.b7039fc61efd261f9da3.js
qiskit_code_assistant_jupyterlab-0.9.0.data/data/share/jupyter/labextensions/qiskit-code-assistant-jupyterlab/static/style.js
qiskit_code_assistant_jupyterlab-0.9.0.data/data/share/jupyter/labextensions/qiskit-code-assistant-jupyterlab/static/third-party-licenses.json
qiskit_code_assistant_jupyterlab-0.9.0.data/data/share/jupyter/labextensions/qiskit-code-assistant-jupyterlab/install.json
qiskit_code_assistant_jupyterlab-0.9.0.dist-info/METADATA
qiskit_code_assistant_jupyterlab-0.9.0.dist-info/WHEEL
qiskit_code_assistant_jupyterlab-0.9.0.dist-info/licenses/LICENSE
qiskit_code_assistant_jupyterlab-0.9.0.dist-info/RECORD
