Metadata-Version: 2.4
Name: qiskit_code_assistant_jupyterlab
Version: 0.9.0
Dynamic: Keywords
Summary: AI Autocomplete JupyterLab extension for Qiskit Code Assistant (Beta)
Project-URL: Homepage, https://github.com/Qiskit/qiskit-code-assistant-jupyterlab
Project-URL: Bug Tracker, https://github.com/Qiskit/qiskit-code-assistant-jupyterlab/issues
Project-URL: Repository, https://github.com/Qiskit/qiskit-code-assistant-jupyterlab.git
Author: IBM
License:                                  Apache License
License-File: LICENSE
Classifier: Framework :: Jupyter
Classifier: Framework :: Jupyter :: JupyterLab
Classifier: Framework :: Jupyter :: JupyterLab :: 4
Classifier: Framework :: Jupyter :: JupyterLab :: Extensions
Classifier: Framework :: Jupyter :: JupyterLab :: Extensions :: Prebuilt
Classifier: License :: OSI Approved :: Apache Software License
Classifier: Programming Language :: Python
Classifier: Programming Language :: Python :: 3
Classifier: Programming Language :: Python :: 3.8
Classifier: Programming Language :: Python :: 3.9
Classifier: Programming Language :: Python :: 3.10
Classifier: Programming Language :: Python :: 3.11
Classifier: Programming Language :: Python :: 3.12
Requires-Python: >=3.8
Requires-Dist: jupyter-server<3,>=2.4.0
Requires-Dist: qiskit-ibm-runtime
Requires-Dist: tornado>=6.2.0
